simpleresource/__init__.py
simpleresource/simpleresource.py
simpleresource/version.py
simpleresource-1.0.0b0.dist-info/METADATA
simpleresource-1.0.0b0.dist-info/WHEEL
simpleresource-1.0.0b0.dist-info/top_level.txt
simpleresource-1.0.0b0.dist-info/RECORD
