Metadata-Version: 2.1
Name: simpleresource
Version: 1.0.0b0
Summary: UNKNOWN
Home-page: https://github.com/yodeng/simpleresource
Author: Deng Yong
Author-email: yodeng@tju.edu.cn
License: BSD
Platform: UNKNOWN
Classifier: Programming Language :: Python
Classifier: Programming Language :: Python :: 2
Classifier: Programming Language :: Python :: 2.7
